[
  {
    "title": "23_德法_新教材 教学大纲",
    "semester": "当前学期",
    "total_hours": 48,
    "content": "课程名称：思想道德与法治\n适用对象：高等学校本专科学生\n建议学时：48学时\n\n一、课程性质与定位\n《思想道德与法治》是落实立德树人根本任务的高校思想政治理论课必修课程。课程以马克思主义为指导，以习近平新时代中国特色社会主义思想为引领，围绕新时代大学生成长成才中的理想信念、人生价值、中国精神、社会主义核心价值观、道德修养和法治素养等核心问题，帮助学生夯实思想道德基础，提升法治意识和实践能力。\n\n二、课程目标\n1. 知识目标：理解人生观、价值观、理想信念、中国精神、社会主义核心价值观、社会主义道德和社会主义法治的基本理论。\n2. 能力目标：能够运用马克思主义立场观点方法分析个人成长、社会责任、道德选择和法治实践中的现实问题。\n3. 素养目标：坚定理想信念，厚植爱国情怀，增强社会责任感、道德判断力、法治意识和实践担当。\n\n三、教学重点\n1. 正确认识个人与社会、人生目的、人生态度和人生价值的关系。\n2. 坚定马克思主义信仰、中国特色社会主义信念和中华民族伟大复兴信心。\n3. 深刻理解中国精神、爱国主义、改革创新和社会主义核心价值观。\n4. 把握社会主义道德的核心、原则、规范和实践要求。\n5. 理解习近平法治思想、社会主义法律的特征运行和全面依法治国的实践要求。\n\n四、教学难点\n1. 引导学生把个人理想融入国家前途、民族命运和人民幸福。\n2. 引导学生在多元社会思潮中形成正确价值判断。\n3. 引导学生把道德认知、法治意识转化为日常行为和社会实践。\n\n五、教学内容与学时安排\n绪论 担当复兴大任 成就时代新人（2学时）\n教学要点：认识新时代大学生的历史方位和使命担当；理解思想道德素质与法治素养对成长成才的重要意义。\n\n第一章 领悟人生真谛 把握人生方向（7学时）\n第一节 人生观是对人生的总看法\n第二节 正确的人生观\n第三节 创造有意义的人生\n教学要点：理解人的本质、人生目的、人生态度和人生价值；能够辨析拜金主义、享乐主义、极端个人主义等错误人生观；引导学生在服务人民、奉献社会中成就出彩人生。\n\n第二章 追求远大理想 坚定崇高信念（7学时）\n第一节 理想信念的内涵及重要性\n第二节 坚定信仰信念信心\n第三节 在实现中国梦的实践中放飞青春梦想\n教学要点：理解理想信念的内涵、类型和作用；坚定马克思主义信仰、中国特色社会主义信念、中华民族伟大复兴信心；把个人理想同中国梦结合起来。\n\n第三章 继承优良传统 弘扬中国精神（7学时）\n第一节 中国精神是兴国强国之魂\n第二节 做新时代的忠诚爱国者\n第三节 让改革创新成为青春远航的动力\n教学要点：理解中国精神的丰富内涵；把握爱国主义的时代要求；理解改革创新精神对新时代青年成长的重要意义。\n\n第四章 明确价值要求 践行价值准则（6学时）\n第一节 全体人民共同的价值追求\n第二节 社会主义核心价值观的显著特征\n第三节 积极践行社会主义核心价值观\n教学要点：理解社会主义核心价值观的基本内容、时代意义和实践要求；引导学生把价值准则落实到学习生活、职业发展和社会交往中。\n\n第五章 遵守道德规范 锤炼道德品格（9学时）\n第一节 社会主义道德的核心与原则\n第二节 吸收借鉴优秀道德成果\n第三节 投身崇德向善的道德实践\n教学要点：理解社会主义道德建设的核心和原则；继承中华传统美德、弘扬中国革命道德、借鉴人类文明优秀道德成果；掌握社会公德、职业道德、家庭美德、个人品德的实践要求。\n\n第六章 学习法治思想 提升法治素养（8学时）\n第一节 社会主义法律的特征和运行\n第二节 坚持全面依法治国\n第三节 维护宪法权威\n第四节 自觉尊法学法守法用法\n教学要点：理解社会主义法律的本质特征和运行机制；学习习近平法治思想；理解宪法精神和全面依法治国要求；提升法治思维和依法办事能力。\n\n实践教学与综合复习（2学时）\n教学要点：围绕红色资源、志愿服务、法治实践、道德观察、主题调研等开展课堂展示或实践交流，完成课程总结与综合提升。\n\n六、教学方法\n采用专题讲授、案例教学、课堂讨论、情景分析、实践研学、主题展示和线上线下混合学习等方式，突出问题导向、价值引领和实践转化。\n\n七、考核方式\n建议采用过程性评价与终结性评价相结合的方式。过程性评价可包括课堂表现、主题讨论、实践报告、学习笔记、小组展示等；终结性评价可采用课程论文、闭卷或开卷测试、综合展示等形式。建议过程性评价占60%，终结性评价占40%，具体比例可根据教学安排调整。\n\n八、教学资源\n1. 《思想道德与法治（2023年版）》教材。\n2. 习近平新时代中国特色社会主义思想相关重要文献。\n3. 新华社、人民网、学习强国等权威时政与案例资源。\n4. 红色场馆、法治教育基地、志愿服务和社会实践资源。",
    "id": "202607041506462be749"
  }
]